{"Results":{"GeneralInfo":{"Timezone":"GMT+0000 (Coordinated Universal Time)","ReportTitle":"UFT Developer Report","OrchestrationToolName":"JUnit","RunStartTime":"2025-02-13 14:21:49"},"ReportNode":{"@type":"Run","Data":{"Extension":{"Any":{"IconKey":"Run","IsHtmlErrorText":"true"}},"Description":{"#cdata-section":" "},"ToolName":"UFT Developer","StartTime":"2025-02-13 14:21:49","Environment":{"Locale":{"#cdata-section":"en-US"},"Timezone":{"#cdata-section":"GMT+0000 (Coordinated Universal Time)"},"OSInfo":{"#cdata-section":"Windows_NT 10.0.17763"},"User":{"#cdata-section":"nimbusclient\\demo"},"NumberOfCores":"4","TotalMemory":"8191","HostName":"nimbusclient"},"Duration":{"#cdata-section":"00:00:25.159"},"ToolVersion":{"#cdata-section":"24.2"},"Name":"Run Results","Result":"Passed"},"ReportNode":{"@type":"Package","Data":{"Extension":{"Any":{"IconKey":"Package","IsHtmlErrorText":"true"}},"Description":{"#cdata-section":"Version: N/A"},"StartTime":"2025-02-13 14:21:50","Duration":{"#cdata-section":"00:00:24.523"},"Result":"Passed"},"ReportNode":{"@type":"Class","Data":{"Extension":{"Any":{"IconKey":"Class","IsHtmlErrorText":"true"}},"StartTime":"2025-02-13 14:21:50","Duration":{"#cdata-section":"00:00:24.522"},"Name":"UFTDeveloperTest","Result":"Passed"},"ReportNode":{"@type":"Test","Data":{"Extension":{"Any":{"IconKey":"Test","IsHtmlErrorText":"true"}},"StartTime":"2025-02-13 14:21:50","Duration":{"#cdata-section":"00:00:24.512"},"Name":"test","Result":"Passed"},"ReportNode":[{"@type":"Step","Data":{"Extension":{"Any":{"IconKey":"Browser","CustomUIElements":{"DescriptionLabel":"Data","FlowTreeNodeCaption":{"#cdata-section":"Browser.\u003cspan class\u003d\u0027emphasis\u0027\u003elaunch(\"Chrome\")\u003c/span\u003e"},"FlowTreeNodeTooltip":{"#cdata-section":"Browser.launch(\"Chrome\")"}},"TestObject":{"OperationData":{"#cdata-section":"\u003cstyle\u003e.ex-table{border-collapse: collapse !important;width: auto;height: auto;}.ex-table,.ex-table tr,.ex-table td{border: 1px solid #c6c6c6;}.ex-table td{padding: 5px 10px;vertical-align: top;width: auto;}.ex-table .ex-name{font-size: 13px;font-weight: bold;background-color: #f3f3f3;white-space: nowrap;}.ex-table .ex-value{color: #5a5a5a;}\u003c/style\u003e\u003ctable class\u003d\u0027ex-table\u0027\u003e\u003ctr\u003e\u003ctd class\u003d\u0027ex-name\u0027\u003ebrowserType\u003c/td\u003e\u003ctd class\u003d\u0027ex-value\u0027\u003eCHROME\u003c/td\u003e\u003c/tr\u003e\u003c/table\u003e\u003cstyle\u003e.ex-table{border-collapse: collapse !important;width: auto;height: auto;}.ex-table,.ex-table tr,.ex-table td{border: 1px solid #c6c6c6;}.ex-table td{padding: 5px 10px;vertical-align: top;width: auto;}.ex-table .ex-name{font-size: 13px;font-weight: bold;background-color: #f3f3f3;white-space: nowrap;}.ex-table .ex-value{color: #5a5a5a;}\u003c/style\u003e\u003cp\u003e\u003cdiv class\u003ddata-label\u003e\u003chr\u003e\u003cb\u003eBrowser Information\u003c/b\u003e\u003c/div\u003e \u003c/p\u003e\u003cstyle\u003e.ex-table{border-collapse: collapse !important;width: auto;height: auto;}.ex-table,.ex-table tr,.ex-table td{border: 1px solid #c6c6c6;}.ex-table td{padding: 5px 10px;vertical-align: top;width: auto;}.ex-table .ex-name{font-size: 13px;font-weight: bold;background-color: #f3f3f3;white-space: nowrap;}.ex-table .ex-value{color: #5a5a5a;}\u003c/style\u003e\u003ctable class\u003d\u0027ex-table\u0027\u003e\u003ctr\u003e\u003ctd class\u003d\u0027ex-name\u0027\u003etype\u003c/td\u003e\u003ctd class\u003d\u0027ex-value\u0027\u003eChrome\u003c/td\u003e\u003c/tr\u003e\u003ctr\u003e\u003ctd class\u003d\u0027ex-name\u0027\u003eversion\u003c/td\u003e\u003ctd class\u003d\u0027ex-value\u0027\u003e132.0\u003c/td\u003e\u003c/tr\u003e\u003ctr\u003e\u003ctd class\u003d\u0027ex-name\u0027\u003emax concurrent tests\u003c/td\u003e\u003ctd class\u003d\u0027ex-value\u0027\u003e9.007199254740991E15\u003c/td\u003e\u003c/tr\u003e\u003ctr\u003e\u003ctd class\u003d\u0027ex-name\u0027\u003eosVersion\u003c/td\u003e\u003ctd class\u003d\u0027ex-value\u0027\u003e10\u003c/td\u003e\u003c/tr\u003e\u003ctr\u003e\u003ctd class\u003d\u0027ex-name\u0027\u003eosType\u003c/td\u003e\u003ctd class\u003d\u0027ex-value\u0027\u003eWindows\u003c/td\u003e\u003c/tr\u003e\u003ctr\u003e\u003ctd class\u003d\u0027ex-name\u0027\u003ename\u003c/td\u003e\u003ctd class\u003d\u0027ex-value\u0027\u003enimbusclient\u003c/td\u003e\u003c/tr\u003e\u003ctr\u003e\u003ctd class\u003d\u0027ex-name\u0027\u003eid\u003c/td\u003e\u003ctd class\u003d\u0027ex-value\u0027\u003enimbusclient\u003c/td\u003e\u003c/tr\u003e\u003c/table\u003e"},"Operation":"launch"},"IsHtmlErrorText":"true","HideContextInfo":"true"}},"Description":{"#cdata-section":"\u003cstyle\u003e.ex-table{border-collapse: collapse !important;width: auto;height: auto;}.ex-table,.ex-table tr,.ex-table td{border: 1px solid #c6c6c6;}.ex-table td{padding: 5px 10px;vertical-align: top;width: auto;}.ex-table .ex-name{font-size: 13px;font-weight: bold;background-color: #f3f3f3;white-space: nowrap;}.ex-table .ex-value{color: #5a5a5a;}\u003c/style\u003e\u003ctable class\u003d\u0027ex-table\u0027\u003e\u003ctr\u003e\u003ctd class\u003d\u0027ex-name\u0027\u003ebrowserType\u003c/td\u003e\u003ctd class\u003d\u0027ex-value\u0027\u003eCHROME\u003c/td\u003e\u003c/tr\u003e\u003c/table\u003e\u003cstyle\u003e.ex-table{border-collapse: collapse !important;width: auto;height: auto;}.ex-table,.ex-table tr,.ex-table td{border: 1px solid #c6c6c6;}.ex-table td{padding: 5px 10px;vertical-align: top;width: auto;}.ex-table .ex-name{font-size: 13px;font-weight: bold;background-color: #f3f3f3;white-space: nowrap;}.ex-table .ex-value{color: #5a5a5a;}\u003c/style\u003e\u003cp\u003e\u003cdiv class\u003ddata-label\u003e\u003chr\u003e\u003cb\u003eBrowser Information\u003c/b\u003e\u003c/div\u003e \u003c/p\u003e\u003cstyle\u003e.ex-table{border-collapse: collapse !important;width: auto;height: auto;}.ex-table,.ex-table tr,.ex-table td{border: 1px solid #c6c6c6;}.ex-table td{padding: 5px 10px;vertical-align: top;width: auto;}.ex-table .ex-name{font-size: 13px;font-weight: bold;background-color: #f3f3f3;white-space: nowrap;}.ex-table .ex-value{color: #5a5a5a;}\u003c/style\u003e\u003ctable class\u003d\u0027ex-table\u0027\u003e\u003ctr\u003e\u003ctd class\u003d\u0027ex-name\u0027\u003etype\u003c/td\u003e\u003ctd class\u003d\u0027ex-value\u0027\u003eChrome\u003c/td\u003e\u003c/tr\u003e\u003ctr\u003e\u003ctd class\u003d\u0027ex-name\u0027\u003eversion\u003c/td\u003e\u003ctd class\u003d\u0027ex-value\u0027\u003e132.0\u003c/td\u003e\u003c/tr\u003e\u003ctr\u003e\u003ctd class\u003d\u0027ex-name\u0027\u003emax concurrent tests\u003c/td\u003e\u003ctd class\u003d\u0027ex-value\u0027\u003e9.007199254740991E15\u003c/td\u003e\u003c/tr\u003e\u003ctr\u003e\u003ctd class\u003d\u0027ex-name\u0027\u003eosVersion\u003c/td\u003e\u003ctd class\u003d\u0027ex-value\u0027\u003e10\u003c/td\u003e\u003c/tr\u003e\u003ctr\u003e\u003ctd class\u003d\u0027ex-name\u0027\u003eosType\u003c/td\u003e\u003ctd class\u003d\u0027ex-value\u0027\u003eWindows\u003c/td\u003e\u003c/tr\u003e\u003ctr\u003e\u003ctd class\u003d\u0027ex-name\u0027\u003ename\u003c/td\u003e\u003ctd class\u003d\u0027ex-value\u0027\u003enimbusclient\u003c/td\u003e\u003c/tr\u003e\u003ctr\u003e\u003ctd class\u003d\u0027ex-name\u0027\u003eid\u003c/td\u003e\u003ctd class\u003d\u0027ex-value\u0027\u003enimbusclient\u003c/td\u003e\u003c/tr\u003e\u003c/table\u003e"},"StartTime":"2025-02-13 14:21:50","Duration":{"#cdata-section":"00:00:00.000"},"Name":{"#cdata-section":"Browser.launch"},"Result":"Passed"}},{"@type":"Step","Data":{"Extension":{"Any":{"IconKey":"Browser","CustomUIElements":{"DescriptionLabel":"Data"},"Descriptive":{"TestObject":{"Path":{"Object":{"IconKey":"Browser","Type":"Web.Browser","Name":{"#cdata-section":"about:blank"}}}}},"TestObject":{"Path":{"Object":{"Type":"Web.Browser","Name":{"#cdata-section":"about:blank"}}},"OperationData":{"#cdata-section":"\u003cstyle\u003e.ex-table{border-collapse: collapse !important;width: auto;height: auto;}.ex-table,.ex-table tr,.ex-table td{border: 1px solid #c6c6c6;}.ex-table td{padding: 5px 10px;vertical-align: top;width: auto;}.ex-table .ex-name{font-size: 13px;font-weight: bold;background-color: #f3f3f3;white-space: nowrap;}.ex-table .ex-value{color: #5a5a5a;}\u003c/style\u003e\u003ctable class\u003d\u0027ex-table\u0027\u003e\u003ctr\u003e\u003ctd class\u003d\u0027ex-name\u0027\u003eurl\u003c/td\u003e\u003ctd class\u003d\u0027ex-value\u0027\u003ehttps://advantageonlineshopping.com/#/\u003c/td\u003e\u003c/tr\u003e\u003c/table\u003e"},"Operation":"navigate","Properties":{"Property":[{"Value":{"#cdata-section":"Chrome"},"Name":{"#cdata-section":"type"}},{"Value":{"#cdata-section":"132.0"},"Name":{"#cdata-section":"version"}},{"Value":{"#cdata-section":"9.007199254740991E15"},"Name":{"#cdata-section":"max concurrent tests"}},{"Value":{"#cdata-section":"10"},"Name":{"#cdata-section":"osVersion"}},{"Value":{"#cdata-section":"Windows"},"Name":{"#cdata-section":"osType"}},{"Value":{"#cdata-section":"nimbusclient"},"Name":{"#cdata-section":"name"}},{"Value":{"#cdata-section":"nimbusclient"},"Name":{"#cdata-section":"id"}}]}},"IsHtmlErrorText":"true","HideContextInfo":"true"}},"Description":{"#cdata-section":"\u003cstyle\u003e.ex-table{border-collapse: collapse !important;width: auto;height: auto;}.ex-table,.ex-table tr,.ex-table td{border: 1px solid #c6c6c6;}.ex-table td{padding: 5px 10px;vertical-align: top;width: auto;}.ex-table .ex-name{font-size: 13px;font-weight: bold;background-color: #f3f3f3;white-space: nowrap;}.ex-table .ex-value{color: #5a5a5a;}\u003c/style\u003e\u003ctable class\u003d\u0027ex-table\u0027\u003e\u003ctr\u003e\u003ctd class\u003d\u0027ex-name\u0027\u003eurl\u003c/td\u003e\u003ctd class\u003d\u0027ex-value\u0027\u003ehttps://advantageonlineshopping.com/#/\u003c/td\u003e\u003c/tr\u003e\u003c/table\u003e"},"StartTime":"2025-02-13 14:22:01","Duration":{"#cdata-section":"00:00:00.146"},"Name":{"#cdata-section":"about:blank.navigate"},"Result":"Passed"}},{"@type":"Step","Data":{"Extension":{"Any":{"IconKey":"Link","CustomUIElements":{"DescriptionLabel":"Data"},"Descriptive":{"TestObject":{"Path":{"Object":[{"IconKey":"Browser","Type":"Web.Browser","Name":{"#cdata-section":"Advantage Shopping"}},{"IconKey":"Page","Type":"Web.Page","Name":{"#cdata-section":"Advantage Shopping"}},{"IconKey":"Link","Type":"Web.Link","Name":{"#cdata-section":"SpeakersCategoryTxt"}}]}}},"TestObject":{"Path":{"Object":[{"Type":"Web.Browser","Name":{"#cdata-section":"Advantage Shopping"}},{"Type":"Web.Page","Name":{"#cdata-section":"Advantage Shopping"}},{"Type":"Web.Link","Name":{"#cdata-section":"SpeakersCategoryTxt"}}]},"Operation":"click","Properties":{"Property":[{"Value":{"#cdata-section":"SPEAKERS"},"Name":{"#cdata-section":"innerText"}},{"Value":{"#cdata-section":"SPAN"},"Name":{"#cdata-section":"tagName"}}]}},"IsHtmlErrorText":"true","HideContextInfo":"true"}},"StartTime":"2025-02-13 14:22:01","Duration":{"#cdata-section":"00:00:08.749"},"Name":{"#cdata-section":"SpeakersCategoryTxt.click"},"Result":"Passed"}},{"@type":"Step","Data":{"Extension":{"Any":{"IconKey":"Button","CustomUIElements":{"DescriptionLabel":"Data"},"Descriptive":{"TestObject":{"Path":{"Object":[{"IconKey":"Browser","Type":"Web.Browser","Name":{"#cdata-section":"Advantage Shopping"}},{"IconKey":"Page","Type":"Web.Page","Name":{"#cdata-section":"Advantage Shopping"}},{"IconKey":"Button","Type":"Web.Button","Name":{"#cdata-section":"buy_now"}}]}}},"TestObject":{"Path":{"Object":[{"Type":"Web.Browser","Name":{"#cdata-section":"Advantage Shopping"}},{"Type":"Web.Page","Name":{"#cdata-section":"Advantage Shopping"}},{"Type":"Web.Button","Name":{"#cdata-section":"buy_now"}}]},"Operation":"click","Properties":{"Property":[{"Value":{"#cdata-section":"submit"},"Name":{"#cdata-section":"buttonType"}},{"Value":{"#cdata-section":"BUY NOW"},"Name":{"#cdata-section":"name"}},{"Value":{"#cdata-section":"BUTTON"},"Name":{"#cdata-section":"tagName"}}]}},"IsHtmlErrorText":"true","HideContextInfo":"true"}},"StartTime":"2025-02-13 14:22:10","Duration":{"#cdata-section":"00:00:01.384"},"Name":{"#cdata-section":"buy_now.click"},"Result":"Passed"}},{"@type":"Step","Data":{"Extension":{"Any":{"IconKey":"Button","CustomUIElements":{"DescriptionLabel":"Data"},"Descriptive":{"TestObject":{"Path":{"Object":[{"IconKey":"Browser","Type":"Web.Browser","Name":{"#cdata-section":"Advantage Shopping"}},{"IconKey":"Page","Type":"Web.Page","Name":{"#cdata-section":"Advantage Shopping"}},{"IconKey":"Button","Type":"Web.Button","Name":{"#cdata-section":"save_to_cart"}}]}}},"TestObject":{"Path":{"Object":[{"Type":"Web.Browser","Name":{"#cdata-section":"Advantage Shopping"}},{"Type":"Web.Page","Name":{"#cdata-section":"Advantage Shopping"}},{"Type":"Web.Button","Name":{"#cdata-section":"save_to_cart"}}]},"Operation":"click","Properties":{"Property":[{"Value":{"#cdata-section":"submit"},"Name":{"#cdata-section":"buttonType"}},{"Value":{"#cdata-section":"ADD TO CART"},"Name":{"#cdata-section":"name"}},{"Value":{"#cdata-section":"BUTTON"},"Name":{"#cdata-section":"tagName"}}]}},"IsHtmlErrorText":"true","HideContextInfo":"true"}},"StartTime":"2025-02-13 14:22:11","Duration":{"#cdata-section":"00:00:01.280"},"Name":{"#cdata-section":"save_to_cart.click"},"Result":"Passed"}},{"@type":"Step","Data":{"Extension":{"Any":{"IconKey":"Link","CustomUIElements":{"DescriptionLabel":"Data"},"Descriptive":{"TestObject":{"Path":{"Object":[{"IconKey":"Browser","Type":"Web.Browser","Name":{"#cdata-section":"Advantage Shopping"}},{"IconKey":"Page","Type":"Web.Page","Name":{"#cdata-section":"Advantage Shopping"}},{"IconKey":"Link","Type":"Web.Link","Name":{"#cdata-section":"ShoppingCart"}}]}}},"TestObject":{"Path":{"Object":[{"Type":"Web.Browser","Name":{"#cdata-section":"Advantage Shopping"}},{"Type":"Web.Page","Name":{"#cdata-section":"Advantage Shopping"}},{"Type":"Web.Link","Name":{"#cdata-section":"ShoppingCart"}}]},"Operation":"click","Properties":{"Property":[{"Value":{"#cdata-section":"link"},"Name":{"#cdata-section":"role"}},{"Value":{"#cdata-section":"ShoppingCart"},"Name":{"#cdata-section":"accessibilityName"}},{"Value":{"#cdata-section":"1 "},"Name":{"#cdata-section":"innerText"}},{"Value":{"#cdata-section":"A"},"Name":{"#cdata-section":"tagName"}}]}},"IsHtmlErrorText":"true","HideContextInfo":"true"}},"StartTime":"2025-02-13 14:22:12","Duration":{"#cdata-section":"00:00:00.114"},"Name":{"#cdata-section":"ShoppingCart.click"},"Result":"Passed"}},{"@type":"Step","Data":{"Extension":{"Any":{"IconKey":"WebElement","CustomUIElements":{"DescriptionLabel":"Data"},"Descriptive":{"TestObject":{"Path":{"Object":[{"IconKey":"Browser","Type":"Web.Browser","Name":{"#cdata-section":"Advantage Shopping"}},{"IconKey":"Page","Type":"Web.Page","Name":{"#cdata-section":"Advantage Shopping"}},{"IconKey":"WebElement","Type":"Web.WebElement","Name":{"#cdata-section":"REMOVE"}}]}}},"TestObject":{"Path":{"Object":[{"Type":"Web.Browser","Name":{"#cdata-section":"Advantage Shopping"}},{"Type":"Web.Page","Name":{"#cdata-section":"Advantage Shopping"}},{"Type":"Web.WebElement","Name":{"#cdata-section":"REMOVE"}}]},"Operation":"click","Properties":{"Property":[{"Value":{"#cdata-section":"REMOVE"},"Name":{"#cdata-section":"innerText"}},{"Value":{"#cdata-section":"A"},"Name":{"#cdata-section":"tagName"}}]}},"IsHtmlErrorText":"true","HideContextInfo":"true"}},"StartTime":"2025-02-13 14:22:12","Duration":{"#cdata-section":"00:00:00.956"},"Name":{"#cdata-section":"REMOVE.click"},"Result":"Passed"}},{"@type":"Step","Data":{"Extension":{"Any":{"IconKey":"Link","CustomUIElements":{"DescriptionLabel":"Data"},"Descriptive":{"TestObject":{"Path":{"Object":[{"IconKey":"Browser","Type":"Web.Browser","Name":{"#cdata-section":"Advantage Shopping"}},{"IconKey":"Page","Type":"Web.Page","Name":{"#cdata-section":"Advantage Shopping"}},{"IconKey":"Link","Type":"Web.Link","Name":{"#cdata-section":"dvantage DEMO"}}]}}},"TestObject":{"Path":{"Object":[{"Type":"Web.Browser","Name":{"#cdata-section":"Advantage Shopping"}},{"Type":"Web.Page","Name":{"#cdata-section":"Advantage Shopping"}},{"Type":"Web.Link","Name":{"#cdata-section":"dvantage DEMO"}}]},"Operation":"click","Properties":{"Property":[{"Value":{"#cdata-section":"dvantage DEMO "},"Name":{"#cdata-section":"innerText"}},{"Value":{"#cdata-section":"A"},"Name":{"#cdata-section":"tagName"}}]}},"IsHtmlErrorText":"true","HideContextInfo":"true"}},"StartTime":"2025-02-13 14:22:13","Duration":{"#cdata-section":"00:00:00.093"},"Name":{"#cdata-section":"dvantage DEMO.click"},"Result":"Passed"}},{"@type":"Step","Data":{"Extension":{"Any":{"IconKey":"Browser","CustomUIElements":{"DescriptionLabel":"Data"},"Descriptive":{"TestObject":{"Path":{"Object":{"IconKey":"Browser","Type":"Web.Browser","Name":{"#cdata-section":"Advantage Shopping"}}}}},"TestObject":{"Path":{"Object":{"Type":"Web.Browser","Name":{"#cdata-section":"Advantage Shopping"}}},"Operation":"close","Properties":{"Property":[{"Value":{"#cdata-section":"Chrome"},"Name":{"#cdata-section":"type"}},{"Value":{"#cdata-section":"132.0"},"Name":{"#cdata-section":"version"}},{"Value":{"#cdata-section":"9.007199254740991E15"},"Name":{"#cdata-section":"max concurrent tests"}},{"Value":{"#cdata-section":"10"},"Name":{"#cdata-section":"osVersion"}},{"Value":{"#cdata-section":"Windows"},"Name":{"#cdata-section":"osType"}},{"Value":{"#cdata-section":"nimbusclient"},"Name":{"#cdata-section":"name"}},{"Value":{"#cdata-section":"nimbusclient"},"Name":{"#cdata-section":"id"}}]}},"IsHtmlErrorText":"true","HideContextInfo":"true"}},"StartTime":"2025-02-13 14:22:13","Duration":{"#cdata-section":"00:00:00.924"},"Name":{"#cdata-section":"Advantage Shopping.close"},"Result":"Passed"}}]}}}}}}
